objectdetectiontools/__init__.py
objectdetectiontools/data.py
objectdetectiontools/images.py
objectdetectiontools/parser.py
objectdetectiontools/reader.py
objectdetectiontools-1.3.4.dist-info/LICENSE
objectdetectiontools-1.3.4.dist-info/METADATA
objectdetectiontools-1.3.4.dist-info/WHEEL
objectdetectiontools-1.3.4.dist-info/top_level.txt
objectdetectiontools-1.3.4.dist-info/RECORD
