Metadata-Version: 2.1
Name: objectdetectiontools
Version: 1.3.4
Summary: A set of functions useful when doing object detection.
Author: Bas Michielsen
License: 
Project-URL: Homepage, https://gitlab.com/bazzz/objectdetectiontools
Keywords: object detection,pvoc,preprocessing
Classifier: License :: Free for non-commercial use
Classifier: Programming Language :: Python
Classifier: Programming Language :: Python :: 3
Requires-Python: >=3.8
License-File: LICENSE
